rhumbix_csv_uploader/__init__.py
rhumbix_csv_uploader/csv_processor.py
rhumbix_csv_uploader/job_cost_processor.py
rhumbix_csv_uploader/payroll_processor.py
rhumbix_csv_uploader/processor_utils.py
rhumbix_csv_uploader/work_order_processor.py
rhumbix_csv_uploader/test/__init__.py
rhumbix_csv_uploader/test/config_test.json
rhumbix_csv_uploader/test/processor_test_config.py
rhumbix_csv_uploader/test/test_job_cost_processor.py
rhumbix_csv_uploader/test/test_payroll_processor.py
rhumbix_csv_uploader/test/test_work_order_processor.py
rhumbix_csv_uploader/test/exampleCSVs/JobCostUpload.csv
rhumbix_csv_uploader/test/exampleCSVs/PayrollUpload.csv
rhumbix_csv_uploader/test/exampleCSVs/WorkOrderUpload.csv
rhumbix_csv_uploader/test/exampleCSVs/rhumbix_job_cost.csv
rhumbix_csv_uploader/test/exampleCSVs/rhumbix_job_cost_2.csv
rhumbix_csv_uploader/test/exampleCSVs/rhumbix_payroll.csv
rhumbix_csv_uploader/test/exampleCSVs/rhumbix_wo.csv
rhumbix_csv_uploader/test/exampleDirectory/rhumbix_job_cost_2.csv
rhumbix_csv_uploader/test/exampleDirectory/rhumbix_payroll.csv
rhumbix_csv_uploader/test/exampleDirectory/rhumbix_wo.csv
rhumbix_csv_uploader-0.0.3.dist-info/DESCRIPTION.rst
rhumbix_csv_uploader-0.0.3.dist-info/METADATA
rhumbix_csv_uploader-0.0.3.dist-info/RECORD
rhumbix_csv_uploader-0.0.3.dist-info/WHEEL
rhumbix_csv_uploader-0.0.3.dist-info/entry_points.txt
rhumbix_csv_uploader-0.0.3.dist-info/metadata.json
rhumbix_csv_uploader-0.0.3.dist-info/pbr.json
rhumbix_csv_uploader-0.0.3.dist-info/top_level.txt
