Metadata-Version: 2.0
Name: rhumbix-csv-uploader
Version: 0.0.3
Summary: Uploads csv data to Rhumbix
Home-page: http://docs.rhumbix.com/rc
Author: Rhumbix
Author-email: dev@rhumbix.com
License: MIT
Platform: UNKNOWN
Classifier: Development Status :: 4 - Beta
Classifier: Environment :: Console
Classifier: Intended Audience :: Developers
Classifier: Intended Audience :: Information Technology
Classifier: License :: OSI Approved :: Apache Software License
Classifier: Operating System :: OS Independent
Classifier: Programming Language :: Python
Requires-Dist: certifi (==2017.7.27.1)
Requires-Dist: chardet (==3.0.4)
Requires-Dist: idna (==2.6)
Requires-Dist: nose (==1.3.7)
Requires-Dist: requests (==2.18.4)
Requires-Dist: urllib3 (==1.22)
